muffin_oauth/__init__.py
muffin_oauth/plugin.py
muffin_oauth/py.typed
muffin_oauth-2.8.1.dist-info/LICENSE
muffin_oauth-2.8.1.dist-info/METADATA
muffin_oauth-2.8.1.dist-info/WHEEL
muffin_oauth-2.8.1.dist-info/RECORD
