Metadata-Version: 2.3
Name: muffin-oauth
Version: 2.8.1
Summary: Support OAuth authentication for Muffin Framework.
License: MIT
Keywords: asgi,asyncio,authorization,muffin,oauth,trio
Author: Kirill Klenov
Author-email: horneds@gmail.com
Requires-Python: >=3.10,<4.0
Classifier: Development Status :: 5 - Production/Stable
Classifier: Framework :: AsyncIO
Classifier: Framework :: Trio
Classifier: Intended Audience :: Developers
Classifier: License :: OSI Approved :: MIT License
Classifier: Programming Language :: Python
Classifier: Programming Language :: Python :: 3
Classifier: Programming Language :: Python :: 3.10
Classifier: Programming Language :: Python :: 3.11
Classifier: Programming Language :: Python :: 3.12
Classifier: Programming Language :: Python :: 3.13
Classifier: Topic :: Internet :: WWW/HTTP
Provides-Extra: uvicorn
Requires-Dist: aioauth-client
Requires-Dist: muffin
Requires-Dist: uvicorn ; extra == "uvicorn"
Project-URL: Homepage, https://github.com/klen/muffin-oauth
Project-URL: Repository, https://github.com/klen/muffin-oauth
